luascli/__init__.py
luascli/__version__.py
luascli/config.py
luascli/exceptions.py
luascli/luas.py
luascli/main.py
luascli/util.py
luascli-0.10.0.dist-info/LICENSE
luascli-0.10.0.dist-info/METADATA
luascli-0.10.0.dist-info/WHEEL
luascli-0.10.0.dist-info/entry_points.txt
luascli-0.10.0.dist-info/top_level.txt
luascli-0.10.0.dist-info/RECORD
