Metadata-Version: 2.1
Name: luascli
Version: 0.10.0
Summary: This is a CLI tool that helps you to get LUAS     Irish Transport information
Home-page: http://github.com/global/luascli
Author: Anderson Goulart
Author-email: global@kokre.io
License: MIT
Platform: UNKNOWN
Classifier: Programming Language :: Python :: 3
Classifier: License :: OSI Approved :: MIT License
Classifier: Operating System :: OS Independent
Requires-Python: >=3.6
Requires-Dist: Click
Requires-Dist: requests
Requires-Dist: xmltodict
